coreschema/__init__.py
coreschema/compat.py
coreschema/formats.py
coreschema/schemas.py
coreschema/utils.py
coreschema/encodings/__init__.py
coreschema/encodings/corejson.py
coreschema/encodings/html.py
coreschema/encodings/jsonschema.py
coreschema/templates/base.html
coreschema/templates/form.html
coreschema/templates/bootstrap3/form.html
coreschema/templates/bootstrap3/inputs/checkbox.html
coreschema/templates/bootstrap3/inputs/input.html
coreschema/templates/bootstrap3/inputs/select.html
coreschema/templates/bootstrap3/inputs/select_multiple.html
coreschema/templates/bootstrap3/inputs/textarea.html
coreschema-0.0.3.dist-info/DESCRIPTION.rst
coreschema-0.0.3.dist-info/METADATA
coreschema-0.0.3.dist-info/RECORD
coreschema-0.0.3.dist-info/WHEEL
coreschema-0.0.3.dist-info/metadata.json
coreschema-0.0.3.dist-info/top_level.txt
